solaredgeoptimizers/__init__.py
solaredgeoptimizers/solaredgeoptimizers.py
solaredgeoptimizers-1.0.12.dist-info/METADATA
solaredgeoptimizers-1.0.12.dist-info/WHEEL
solaredgeoptimizers-1.0.12.dist-info/licenses/LICENSE
solaredgeoptimizers-1.0.12.dist-info/RECORD
