Metadata-Version: 2.1
Name: solaredgeoptimizers
Version: 1.0.12
Summary: A package to communitate with the solaradge portal
Project-URL: Homepage, https://github.com/ProudElm/packaging_solaredgeoptimizers
Project-URL: Bug Tracker, https://github.com/ProudElm/packaging_solaredgeoptimizers/issues
Author-email: Job van de Sande <jobvandesande@outlook.com>
License-File: LICENSE
Classifier: License :: OSI Approved :: MIT License
Classifier: Operating System :: OS Independent
Classifier: Programming Language :: Python :: 3
Requires-Python: >=3.7
